octoliner/__init__.py
octoliner/__main__.py
octoliner/example.py
octoliner/gpioexp.py
octoliner/octoliner.py
octoliner-2.1.0.dist-info/LICENSE
octoliner-2.1.0.dist-info/METADATA
octoliner-2.1.0.dist-info/WHEEL
octoliner-2.1.0.dist-info/top_level.txt
octoliner-2.1.0.dist-info/RECORD
