Metadata-Version: 2.1
Name: octoliner
Version: 2.1.0
Summary: Raspberry Pi library for working with Amperka Octoliner line sensor board
Home-page: https://github.com/amperka/OctolinerPi/
Author: Amperka LLC
Author-email: dev@amperka.com
License: GPLv3
Platform: UNKNOWN
Classifier: Programming Language :: Python :: 3
Classifier: Programming Language :: Python :: 3.7
Requires-Dist: wiringpi
